trueway_geocoding_rapidapi/__init__.py
trueway_geocoding_rapidapi/api.py
trueway_geocoding_rapidapi/schemas/__init__.py
trueway_geocoding_rapidapi/schemas/base.py
trueway_geocoding_rapidapi/schemas/enums.py
trueway_geocoding_rapidapi/schemas/schema.py
trueway_geocoding_rapidapi-0.2.3.dist-info/LICENSE
trueway_geocoding_rapidapi-0.2.3.dist-info/METADATA
trueway_geocoding_rapidapi-0.2.3.dist-info/WHEEL
trueway_geocoding_rapidapi-0.2.3.dist-info/top_level.txt
trueway_geocoding_rapidapi-0.2.3.dist-info/RECORD
