Metadata-Version: 2.1
Name: trueway-geocoding-rapidapi
Version: 0.2.3
Summary: TrueWay Geocoding API on RapidAPI
Home-page: https://github.com/dankaprogg/trueway_geocoding_rapidapi
Author: Daniil Shvedov
Author-email: dshvedov@kotspin.ru
Keywords: rapidapi,trueway,geocoding
License-File: LICENSE
